tangram_airports/AirportSearchWidget.vue
tangram_airports/__init__.py
tangram_airports/index.ts
tangram_airports/dist-frontend/index.css
tangram_airports/dist-frontend/index.js
tangram_airports/dist-frontend/index.js.map
tangram_airports/dist-frontend/plugin.json
tangram_airports/package.json
tangram_airports-0.2.1.dist-info/METADATA
tangram_airports-0.2.1.dist-info/WHEEL
tangram_airports-0.2.1.dist-info/entry_points.txt
tangram_airports-0.2.1.dist-info/RECORD
